{"53":{"money":11000,"cframe":"432.287415, 45.9230843, 371.384125, 1, 0, 0, 0, 1, 0, 0, 0, 1","type":"upgrade_unit_ingame","unit":"homura_evolved"},"43":{"money":6000,"cframe":"417.002167, 45.9230804, 347.831451, 1, 0, 0, 0, 1, 0, 0, 0, 1","type":"upgrade_unit_ingame","unit":"homura_evolved"},"51":{"money":6000,"cframe":"432.287415, 45.9230843, 371.384125, 1, 0, 0, 0, 1, 0, 0, 0, 1","type":"upgrade_unit_ingame","unit":"homura_evolved"},"41":{"money":3500,"cframe":"417.002167, 45.9230804, 347.831451, 1, 0, 0, 0, 1, 0, 0, 0, 1","type":"upgrade_unit_ingame","unit":"homura_evolved"},"47":{"money":2000,"cframe":"432.287415, 45.9230843, 371.384125, 1, 0, 0, 0, 1, 0, 0, 0, 1","type":"upgrade_unit_ingame","unit":"homura_evolved"},"37":{"money":100000,"cframe":"408.478882, 45.9230843, 369.573578, 1, 0, 0, 0, 1, 0, 0, 0, 1","type":"upgrade_unit_ingame","unit":"ainz_evolved"},"45":{"money":11000,"cframe":"417.002167, 45.9230804, 347.831451, 1, 0, 0, 0, 1, 0, 0, 0, 1","type":"upgrade_unit_ingame","unit":"homura_evolved"},"35":{"money":10000,"cframe":"402.420746, 45.9230843, 367.388489, 1, 0, 0, 0, 1, 0, 0, 0, 1","type":"upgrade_unit_ingame","unit":"stain_evolved"},"59":{"money":20000,"cframe":"417.002167, 45.9230804, 347.831451, 1, 0, 0, 0, 1, 0, 0, 0, 1","type":"upgrade_unit_ingame","unit":"homura_evolved"},"49":{"money":3500,"cframe":"432.287415, 45.9230843, 371.384125, 1, 0, 0, 0, 1, 0, 0, 0, 1","type":"upgrade_unit_ingame","unit":"homura_evolved"},"39":{"money":2000,"cframe":"417.002167, 45.9230804, 347.831451, 1, 0, 0, 0, 1, 0, 0, 0, 1","type":"upgrade_unit_ingame","unit":"homura_evolved"},"29":{"money":2100,"cframe":"402.420746, 45.9230843, 367.388489, 1, 0, 0, 0, 1, 0, 0, 0, 1","type":"upgrade_unit_ingame","unit":"stain_evolved"},"10":{"money":1600,"cframe":"403.413177, 45.9230843, 373.168762, 1, 0, 0, 0, 1, 0, 0, 0, 1","type":"spawn_unit","unit":"homura_evolved"},"57":{"money":15000,"cframe":"417.002167, 45.9230804, 347.831451, 1, 0, 0, 0, 1, 0, 0, 0, 1","type":"upgrade_unit_ingame","unit":"homura_evolved"},"12":{"money":7500,"cframe":"408.478882, 45.9230843, 369.573578, 1, 0, 0, 0, 1, 0, 0, 0, 1","type":"upgrade_unit_ingame","unit":"ainz_evolved"},"1":{"money":800,"cframe":"409.073273, 45.9230843, 377.419189, 1, 0, 0, 0, 1, 0, 0, 0, 1","type":"spawn_unit","unit":"bulma"},"34":{"money":8000,"cframe":"402.420746, 45.9230843, 367.388489, 1, 0, 0, 0, 1, 0, 0, 0, 1","type":"upgrade_unit_ingame","unit":"stain_evolved"},"3":{"money":3000,"cframe":"409.073273, 45.9230843, 377.419189, 1, 0, 0, 0, 1, 0, 0, 0, 1","type":"upgrade_unit_ingame","unit":"bulma"},"2":{"money":1500,"cframe":"409.073273, 45.9230843, 377.419189, 1, 0, 0, 0, 1, 0, 0, 0, 1","type":"upgrade_unit_ingame","unit":"bulma"},"5":{"money":4500,"cframe":"409.073273, 45.9230843, 377.419189, 1, 0, 0, 0, 1, 0, 0, 0, 1","type":"upgrade_unit_ingame","unit":"bulma"},"4":{"money":1500,"cframe":"402.420746, 45.9230843, 367.388489, 1, 0, 0, 0, 1, 0, 0, 0, 1","type":"spawn_unit","unit":"stain_evolved"},"7":{"money":7500,"cframe":"409.073273, 45.9230843, 377.419189, 1, 0, 0, 0, 1, 0, 0, 0, 1","type":"upgrade_unit_ingame","unit":"bulma"},"6":{"money":10000,"cframe":"408.478882, 45.9230843, 369.573578, 1, 0, 0, 0, 1, 0, 0, 0, 1","type":"spawn_unit","unit":"ainz_evolved"},"9":{"money":12500,"cframe":"409.073273, 45.9230843, 377.419189, 1, 0, 0, 0, 1, 0, 0, 0, 1","type":"upgrade_unit_ingame","unit":"bulma"},"8":{"money":10000,"cframe":"409.073273, 45.9230843, 377.419189, 1, 0, 0, 0, 1, 0, 0, 0, 1","type":"upgrade_unit_ingame","unit":"bulma"},"27":{"money":800,"cframe":"400.912842, 45.9230843, 363.620758, 1, 0, 0, 0, 1, 0, 0, 0, 1","type":"spawn_unit","unit":"wendy"},"17":{"money":2500,"cframe":"403.413177, 45.9230843, 373.168762, 1, 0, 0, 0, 1, 0, 0, 0, 1","type":"upgrade_unit_ingame","unit":"homura_evolved"},"13":{"money":12500,"cframe":"408.478882, 45.9230843, 369.573578, 1, 0, 0, 0, 1, 0, 0, 0, 1","type":"upgrade_unit_ingame","unit":"ainz_evolved"},"21":{"money":8000,"cframe":"403.413177, 45.9230843, 373.168762, 1, 0, 0, 0, 1, 0, 0, 0, 1","type":"upgrade_unit_ingame","unit":"homura_evolved"},"11":{"money":5000,"cframe":"408.478882, 45.9230843, 369.573578, 1, 0, 0, 0, 1, 0, 0, 0, 1","type":"upgrade_unit_ingame","unit":"ainz_evolved"},"23":{"money":25000,"cframe":"408.478882, 45.9230843, 369.573578, 1, 0, 0, 0, 1, 0, 0, 0, 1","type":"upgrade_unit_ingame","unit":"ainz_evolved"},"60":{"money":12000,"cframe":"402.420746, 45.9230843, 367.388489, 1, 0, 0, 0, 1, 0, 0, 0, 1","type":"upgrade_unit_ingame","unit":"stain_evolved"},"52":{"money":8000,"cframe":"432.287415, 45.9230843, 371.384125, 1, 0, 0, 0, 1, 0, 0, 0, 1","type":"upgrade_unit_ingame","unit":"homura_evolved"},"40":{"money":2500,"cframe":"417.002167, 45.9230804, 347.831451, 1, 0, 0, 0, 1, 0, 0, 0, 1","type":"upgrade_unit_ingame","unit":"homura_evolved"},"36":{"money":75000,"cframe":"408.478882, 45.9230843, 369.573578, 1, 0, 0, 0, 1, 0, 0, 0, 1","type":"upgrade_unit_ingame","unit":"ainz_evolved"},"46":{"money":1600,"cframe":"432.287415, 45.9230843, 371.384125, 1, 0, 0, 0, 1, 0, 0, 0, 1","type":"spawn_unit","unit":"homura_evolved"},"56":{"money":15000,"cframe":"432.287415, 45.9230843, 371.384125, 1, 0, 0, 0, 1, 0, 0, 0, 1","type":"upgrade_unit_ingame","unit":"homura_evolved"},"44":{"money":8000,"cframe":"417.002167, 45.9230804, 347.831451, 1, 0, 0, 0, 1, 0, 0, 0, 1","type":"upgrade_unit_ingame","unit":"homura_evolved"},"48":{"money":2500,"cframe":"432.287415, 45.9230843, 371.384125, 1, 0, 0, 0, 1, 0, 0, 0, 1","type":"upgrade_unit_ingame","unit":"homura_evolved"},"58":{"money":20000,"cframe":"432.287415, 45.9230843, 371.384125, 1, 0, 0, 0, 1, 0, 0, 0, 1","type":"upgrade_unit_ingame","unit":"homura_evolved"},"28":{"money":35000,"cframe":"408.478882, 45.9230843, 369.573578, 1, 0, 0, 0, 1, 0, 0, 0, 1","type":"upgrade_unit_ingame","unit":"ainz_evolved"},"38":{"money":1600,"cframe":"417.002167, 45.9230804, 347.831451, 1, 0, 0, 0, 1, 0, 0, 0, 1","type":"spawn_unit","unit":"homura_evolved"},"55":{"money":20000,"cframe":"403.413177, 45.9230843, 373.168762, 1, 0, 0, 0, 1, 0, 0, 0, 1","type":"upgrade_unit_ingame","unit":"homura_evolved"},"54":{"money":15000,"cframe":"403.413177, 45.9230843, 373.168762, 1, 0, 0, 0, 1, 0, 0, 0, 1","type":"upgrade_unit_ingame","unit":"homura_evolved"},"50":{"money":4500,"cframe":"432.287415, 45.9230843, 371.384125, 1, 0, 0, 0, 1, 0, 0, 0, 1","type":"upgrade_unit_ingame","unit":"homura_evolved"},"33":{"money":6500,"cframe":"402.420746, 45.9230843, 367.388489, 1, 0, 0, 0, 1, 0, 0, 0, 1","type":"upgrade_unit_ingame","unit":"stain_evolved"},"15":{"money":20000,"cframe":"408.478882, 45.9230843, 369.573578, 1, 0, 0, 0, 1, 0, 0, 0, 1","type":"upgrade_unit_ingame","unit":"ainz_evolved"},"25":{"money":800,"cframe":"400.354431, 45.9230843, 367.833496, 1, 0, 0, 0, 1, 0, 0, 0, 1","type":"spawn_unit","unit":"wendy"},"42":{"money":4500,"cframe":"417.002167, 45.9230804, 347.831451, 1, 0, 0, 0, 1, 0, 0, 0, 1","type":"upgrade_unit_ingame","unit":"homura_evolved"},"19":{"money":4500,"cframe":"403.413177, 45.9230843, 373.168762, 1, 0, 0, 0, 1, 0, 0, 0, 1","type":"upgrade_unit_ingame","unit":"homura_evolved"},"Units":[],"18":{"money":3500,"cframe":"403.413177, 45.9230843, 373.168762, 1, 0, 0, 0, 1, 0, 0, 0, 1","type":"upgrade_unit_ingame","unit":"homura_evolved"},"31":{"money":3500,"cframe":"402.420746, 45.9230843, 367.388489, 1, 0, 0, 0, 1, 0, 0, 0, 1","type":"upgrade_unit_ingame","unit":"stain_evolved"},"61":{"money":15000,"cframe":"402.420746, 45.9230843, 367.388489, 1, 0, 0, 0, 1, 0, 0, 0, 1","type":"upgrade_unit_ingame","unit":"stain_evolved"},"14":{"money":15000,"cframe":"408.478882, 45.9230843, 369.573578, 1, 0, 0, 0, 1, 0, 0, 0, 1","type":"upgrade_unit_ingame","unit":"ainz_evolved"},"24":{"money":800,"cframe":"401.398438, 45.9230843, 369.786194, 1, 0, 0, 0, 1, 0, 0, 0, 1","type":"spawn_unit","unit":"wendy"},"16":{"money":2000,"cframe":"403.413177, 45.9230843, 373.168762, 1, 0, 0, 0, 1, 0, 0, 0, 1","type":"upgrade_unit_ingame","unit":"homura_evolved"},"26":{"money":800,"cframe":"400.336304, 45.9230843, 365.648743, 1, 0, 0, 0, 1, 0, 0, 0, 1","type":"spawn_unit","unit":"wendy"},"20":{"money":6000,"cframe":"403.413177, 45.9230843, 373.168762, 1, 0, 0, 0, 1, 0, 0, 0, 1","type":"upgrade_unit_ingame","unit":"homura_evolved"},"30":{"money":3000,"cframe":"402.420746, 45.9230843, 367.388489, 1, 0, 0, 0, 1, 0, 0, 0, 1","type":"upgrade_unit_ingame","unit":"stain_evolved"},"22":{"money":11000,"cframe":"403.413177, 45.9230843, 373.168762, 1, 0, 0, 0, 1, 0, 0, 0, 1","type":"upgrade_unit_ingame","unit":"homura_evolved"},"32":{"money":5000,"cframe":"402.420746, 45.9230843, 367.388489, 1, 0, 0, 0, 1, 0, 0, 0, 1","type":"upgrade_unit_ingame","unit":"stain_evolved"}}